<?xml version="1.0" encoding="UTF-8"?>
<export version="E">
  <design>
    <source>C:\elektronika\ZDG_ELEKTRONIKA_D-class_AMP\ZDG_ELEKTRONIKA_D-class_AMP.kicad_sch</source>
    <date>21.11.2023 13:05:50</date>
    <tool>Eeschema 7.0.2</tool>
    <sheet number="1" name="/" tstamps="/">
      <title_block>
        <title/>
        <company/>
        <rev/>
        <date/>
        <source>ZDG_ELEKTRONIKA_D-class_AMP.kicad_sch</source>
        <comment number="1" value=""/>
        <comment number="2" value=""/>
        <comment number="3" value=""/>
        <comment number="4" value=""/>
        <comment number="5" value=""/>
        <comment number="6" value=""/>
        <comment number="7" value=""/>
        <comment number="8" value=""/>
        <comment number="9" value=""/>
      </title_block>
    </sheet>
  </design>
  <components>
    <comp ref="C1">
      <value>100uF</value>
      <footprint>Capacitor_SMD:CP_Elec_4x5.4</footprint>
      <fields>
        <field name="LCSC">C177135</field>
        <field name="Note">extended</field>
      </fields>
      <libsource lib="Device" part="C_Polarized" description="Polarized capacitor"/>
      <property name="LCSC" value="C177135"/>
      <property name="Note" value="extended"/>
      <property name="Sheetname" value=""/>
      <property name="Sheetfile" value="ZDG_ELEKTRONIKA_D-class_AMP.kicad_sch"/>
      <property name="ki_description" value="Polarized capacitor"/>
      <property name="ki_keywords" value="cap capacitor"/>
      <sheetpath names="/" tstamps="/"/>
      <tstamps>59625554-d495-4e48-aa60-d1e70c81d049</tstamps>
    </comp>
    <comp ref="C2">
      <value>100nF</value>
      <footprint>Capacitor_SMD:C_0603_1608Metric_Pad1.08x0.95mm_HandSolder</footprint>
      <fields>
        <field name="LCSC">C14663</field>
      </fields>
      <libsource lib="Device" part="C" description="Unpolarized capacitor"/>
      <property name="LCSC" value="C14663"/>
      <property name="Sheetname" value=""/>
      <property name="Sheetfile" value="ZDG_ELEKTRONIKA_D-class_AMP.kicad_sch"/>
      <property name="ki_description" value="Unpolarized capacitor"/>
      <property name="ki_keywords" value="cap capacitor"/>
      <sheetpath names="/" tstamps="/"/>
      <tstamps>36d49042-da96-445e-bc04-e7efef9ad087</tstamps>
    </comp>
    <comp ref="C3">
      <value>1nF</value>
      <footprint>Capacitor_SMD:C_0603_1608Metric_Pad1.08x0.95mm_HandSolder</footprint>
      <fields>
        <field name="LCSC">C1588</field>
      </fields>
      <libsource lib="Device" part="C" description="Unpolarized capacitor"/>
      <property name="LCSC" value="C1588"/>
      <property name="Sheetname" value=""/>
      <property name="Sheetfile" value="ZDG_ELEKTRONIKA_D-class_AMP.kicad_sch"/>
      <property name="ki_description" value="Unpolarized capacitor"/>
      <property name="ki_keywords" value="cap capacitor"/>
      <sheetpath names="/" tstamps="/"/>
      <tstamps>acf9d485-01ec-4286-acef-41630b9b2725</tstamps>
    </comp>
    <comp ref="C4">
      <value>100uF</value>
      <footprint>Capacitor_SMD:CP_Elec_4x5.4</footprint>
      <fields>
        <field name="LCSC">C177135</field>
        <field name="Note">extended</field>
      </fields>
      <libsource lib="Device" part="C_Polarized" description="Polarized capacitor"/>
      <property name="LCSC" value="C177135"/>
      <property name="Note" value="extended"/>
      <property name="Sheetname" value=""/>
      <property name="Sheetfile" value="ZDG_ELEKTRONIKA_D-class_AMP.kicad_sch"/>
      <property name="ki_description" value="Polarized capacitor"/>
      <property name="ki_keywords" value="cap capacitor"/>
      <sheetpath names="/" tstamps="/"/>
      <tstamps>165a320d-db85-462f-98ae-a17a8a2592fe</tstamps>
    </comp>
    <comp ref="C5">
      <value>100nF</value>
      <footprint>Capacitor_SMD:C_0603_1608Metric_Pad1.08x0.95mm_HandSolder</footprint>
      <fields>
        <field name="LCSC">C14663</field>
      </fields>
      <libsource lib="Device" part="C" description="Unpolarized capacitor"/>
      <property name="LCSC" value="C14663"/>
      <property name="Sheetname" value=""/>
      <property name="Sheetfile" value="ZDG_ELEKTRONIKA_D-class_AMP.kicad_sch"/>
      <property name="ki_description" value="Unpolarized capacitor"/>
      <property name="ki_keywords" value="cap capacitor"/>
      <sheetpath names="/" tstamps="/"/>
      <tstamps>c6b00d64-e536-415a-8618-faffe26f01c2</tstamps>
    </comp>
    <comp ref="C6">
      <value>1nF</value>
      <footprint>Capacitor_SMD:C_0603_1608Metric_Pad1.08x0.95mm_HandSolder</footprint>
      <fields>
        <field name="LCSC">C1588</field>
      </fields>
      <libsource lib="Device" part="C" description="Unpolarized capacitor"/>
      <property name="LCSC" value="C1588"/>
      <property name="Sheetname" value=""/>
      <property name="Sheetfile" value="ZDG_ELEKTRONIKA_D-class_AMP.kicad_sch"/>
      <property name="ki_description" value="Unpolarized capacitor"/>
      <property name="ki_keywords" value="cap capacitor"/>
      <sheetpath names="/" tstamps="/"/>
      <tstamps>a33d08f3-eea9-4a5f-877b-5de1cfddebc8</tstamps>
    </comp>
    <comp ref="C7">
      <value>1uF</value>
      <footprint>Capacitor_SMD:C_0603_1608Metric_Pad1.08x0.95mm_HandSolder</footprint>
      <fields>
        <field name="LCSC">C15849</field>
      </fields>
      <libsource lib="Device" part="C" description="Unpolarized capacitor"/>
      <property name="LCSC" value="C15849"/>
      <property name="Sheetname" value=""/>
      <property name="Sheetfile" value="ZDG_ELEKTRONIKA_D-class_AMP.kicad_sch"/>
      <property name="ki_description" value="Unpolarized capacitor"/>
      <property name="ki_keywords" value="cap capacitor"/>
      <sheetpath names="/" tstamps="/"/>
      <tstamps>3d17cefa-6c6a-46dd-8f64-2d1271fbbd7e</tstamps>
    </comp>
    <comp ref="C8">
      <value>1uF</value>
      <footprint>Capacitor_SMD:C_0603_1608Metric_Pad1.08x0.95mm_HandSolder</footprint>
      <fields>
        <field name="LCSC">C15849</field>
      </fields>
      <libsource lib="Device" part="C" description="Unpolarized capacitor"/>
      <property name="LCSC" value="C15849"/>
      <property name="Sheetname" value=""/>
      <property name="Sheetfile" value="ZDG_ELEKTRONIKA_D-class_AMP.kicad_sch"/>
      <property name="ki_description" value="Unpolarized capacitor"/>
      <property name="ki_keywords" value="cap capacitor"/>
      <sheetpath names="/" tstamps="/"/>
      <tstamps>9f08ee7b-5af4-42ac-a6ae-194b97b8e0ac</tstamps>
    </comp>
    <comp ref="C9">
      <value>1uF</value>
      <footprint>Capacitor_SMD:C_0603_1608Metric_Pad1.08x0.95mm_HandSolder</footprint>
      <fields>
        <field name="LCSC">C15849</field>
      </fields>
      <libsource lib="Device" part="C" description="Unpolarized capacitor"/>
      <property name="LCSC" value="C15849"/>
      <property name="Sheetname" value=""/>
      <property name="Sheetfile" value="ZDG_ELEKTRONIKA_D-class_AMP.kicad_sch"/>
      <property name="ki_description" value="Unpolarized capacitor"/>
      <property name="ki_keywords" value="cap capacitor"/>
      <sheetpath names="/" tstamps="/"/>
      <tstamps>39321d73-e85a-4e8b-950f-046109e3d40f</tstamps>
    </comp>
    <comp ref="C10">
      <value>1uF</value>
      <footprint>Capacitor_SMD:C_0603_1608Metric_Pad1.08x0.95mm_HandSolder</footprint>
      <fields>
        <field name="LCSC">C15849</field>
      </fields>
      <libsource lib="Device" part="C" description="Unpolarized capacitor"/>
      <property name="LCSC" value="C15849"/>
      <property name="Sheetname" value=""/>
      <property name="Sheetfile" value="ZDG_ELEKTRONIKA_D-class_AMP.kicad_sch"/>
      <property name="ki_description" value="Unpolarized capacitor"/>
      <property name="ki_keywords" value="cap capacitor"/>
      <sheetpath names="/" tstamps="/"/>
      <tstamps>e99813c0-e007-47f0-874e-507344b1cdc5</tstamps>
    </comp>
    <comp ref="C11">
      <value>470nF</value>
      <footprint>Capacitor_SMD:C_0603_1608Metric_Pad1.08x0.95mm_HandSolder</footprint>
      <fields>
        <field name="LCSC">C1623</field>
      </fields>
      <libsource lib="Device" part="C" description="Unpolarized capacitor"/>
      <property name="LCSC" value="C1623"/>
      <property name="Sheetname" value=""/>
      <property name="Sheetfile" value="ZDG_ELEKTRONIKA_D-class_AMP.kicad_sch"/>
      <property name="ki_description" value="Unpolarized capacitor"/>
      <property name="ki_keywords" value="cap capacitor"/>
      <sheetpath names="/" tstamps="/"/>
      <tstamps>0b303240-b050-49f4-99ab-6eef142b9289</tstamps>
    </comp>
    <comp ref="C12">
      <value>470nF</value>
      <footprint>Capacitor_SMD:C_0603_1608Metric_Pad1.08x0.95mm_HandSolder</footprint>
      <fields>
        <field name="LCSC">C1623</field>
      </fields>
      <libsource lib="Device" part="C" description="Unpolarized capacitor"/>
      <property name="LCSC" value="C1623"/>
      <property name="Sheetname" value=""/>
      <property name="Sheetfile" value="ZDG_ELEKTRONIKA_D-class_AMP.kicad_sch"/>
      <property name="ki_description" value="Unpolarized capacitor"/>
      <property name="ki_keywords" value="cap capacitor"/>
      <sheetpath names="/" tstamps="/"/>
      <tstamps>57de6322-2bf4-443f-8b77-57aa21bee387</tstamps>
    </comp>
    <comp ref="C13">
      <value>1uF</value>
      <footprint>Capacitor_SMD:C_0603_1608Metric_Pad1.08x0.95mm_HandSolder</footprint>
      <fields>
        <field name="LCSC">C15849</field>
      </fields>
      <libsource lib="Device" part="C" description="Unpolarized capacitor"/>
      <property name="LCSC" value="C15849"/>
      <property name="Sheetname" value=""/>
      <property name="Sheetfile" value="ZDG_ELEKTRONIKA_D-class_AMP.kicad_sch"/>
      <property name="ki_description" value="Unpolarized capacitor"/>
      <property name="ki_keywords" value="cap capacitor"/>
      <sheetpath names="/" tstamps="/"/>
      <tstamps>648a327b-0561-4bb0-8027-caf3b949be8c</tstamps>
    </comp>
    <comp ref="C14">
      <value>1uF</value>
      <footprint>Capacitor_SMD:C_0603_1608Metric_Pad1.08x0.95mm_HandSolder</footprint>
      <fields>
        <field name="LCSC">C15849</field>
      </fields>
      <libsource lib="Device" part="C" description="Unpolarized capacitor"/>
      <property name="LCSC" value="C15849"/>
      <property name="Sheetname" value=""/>
      <property name="Sheetfile" value="ZDG_ELEKTRONIKA_D-class_AMP.kicad_sch"/>
      <property name="ki_description" value="Unpolarized capacitor"/>
      <property name="ki_keywords" value="cap capacitor"/>
      <sheetpath names="/" tstamps="/"/>
      <tstamps>b4645de1-2921-43a8-b799-ce5f3db7f8b5</tstamps>
    </comp>
    <comp ref="C15">
      <value>100nF</value>
      <footprint>Capacitor_SMD:C_0603_1608Metric_Pad1.08x0.95mm_HandSolder</footprint>
      <fields>
        <field name="LCSC">C14663</field>
      </fields>
      <libsource lib="Device" part="C" description="Unpolarized capacitor"/>
      <property name="LCSC" value="C14663"/>
      <property name="Sheetname" value=""/>
      <property name="Sheetfile" value="ZDG_ELEKTRONIKA_D-class_AMP.kicad_sch"/>
      <property name="ki_description" value="Unpolarized capacitor"/>
      <property name="ki_keywords" value="cap capacitor"/>
      <sheetpath names="/" tstamps="/"/>
      <tstamps>ac659bc0-5cd2-46ab-be1c-f7b1fa543bab</tstamps>
    </comp>
    <comp ref="C16">
      <value>100nF</value>
      <footprint>Capacitor_SMD:C_0603_1608Metric_Pad1.08x0.95mm_HandSolder</footprint>
      <fields>
        <field name="LCSC">C14663</field>
      </fields>
      <libsource lib="Device" part="C" description="Unpolarized capacitor"/>
      <property name="LCSC" value="C14663"/>
      <property name="Sheetname" value=""/>
      <property name="Sheetfile" value="ZDG_ELEKTRONIKA_D-class_AMP.kicad_sch"/>
      <property name="ki_description" value="Unpolarized capacitor"/>
      <property name="ki_keywords" value="cap capacitor"/>
      <sheetpath names="/" tstamps="/"/>
      <tstamps>6355e3b7-33d5-4b03-b53c-cfe600fb0c35</tstamps>
    </comp>
    <comp ref="C17">
      <value>100nF</value>
      <footprint>Capacitor_SMD:C_0603_1608Metric_Pad1.08x0.95mm_HandSolder</footprint>
      <fields>
        <field name="LCSC">C14663</field>
      </fields>
      <libsource lib="Device" part="C" description="Unpolarized capacitor"/>
      <property name="LCSC" value="C14663"/>
      <property name="Sheetname" value=""/>
      <property name="Sheetfile" value="ZDG_ELEKTRONIKA_D-class_AMP.kicad_sch"/>
      <property name="ki_description" value="Unpolarized capacitor"/>
      <property name="ki_keywords" value="cap capacitor"/>
      <sheetpath names="/" tstamps="/"/>
      <tstamps>4ca1d893-6897-4a5f-8827-6f2cc555682a</tstamps>
    </comp>
    <comp ref="C18">
      <value>100nF</value>
      <footprint>Capacitor_SMD:C_0603_1608Metric_Pad1.08x0.95mm_HandSolder</footprint>
      <fields>
        <field name="LCSC">C14663</field>
      </fields>
      <libsource lib="Device" part="C" description="Unpolarized capacitor"/>
      <property name="LCSC" value="C14663"/>
      <property name="Sheetname" value=""/>
      <property name="Sheetfile" value="ZDG_ELEKTRONIKA_D-class_AMP.kicad_sch"/>
      <property name="ki_description" value="Unpolarized capacitor"/>
      <property name="ki_keywords" value="cap capacitor"/>
      <sheetpath names="/" tstamps="/"/>
      <tstamps>8fb7d04b-2526-4d39-92b9-90a3a2b7f352</tstamps>
    </comp>
    <comp ref="D1">
      <value>D_TVS</value>
      <footprint>Diode_SMD:D_SMA-SMB_Universal_Handsoldering</footprint>
      <libsource lib="Device" part="D_TVS" description="Bidirectional transient-voltage-suppression diode"/>
      <property name="Sheetname" value=""/>
      <property name="Sheetfile" value="ZDG_ELEKTRONIKA_D-class_AMP.kicad_sch"/>
      <property name="ki_description" value="Bidirectional transient-voltage-suppression diode"/>
      <property name="ki_keywords" value="diode TVS thyrector"/>
      <sheetpath names="/" tstamps="/"/>
      <tstamps>c1e72a86-be2a-49ca-a0bf-58718dd2b7f0</tstamps>
    </comp>
    <comp ref="D2">
      <value>RED</value>
      <footprint>LED_SMD:LED_0603_1608Metric_Pad1.05x0.95mm_HandSolder</footprint>
      <fields>
        <field name="LCSC">C2286</field>
      </fields>
      <libsource lib="Device" part="LED" description="Light emitting diode"/>
      <property name="LCSC" value="C2286"/>
      <property name="Sheetname" value=""/>
      <property name="Sheetfile" value="ZDG_ELEKTRONIKA_D-class_AMP.kicad_sch"/>
      <property name="ki_description" value="Light emitting diode"/>
      <property name="ki_keywords" value="LED diode"/>
      <sheetpath names="/" tstamps="/"/>
      <tstamps>21c13232-737a-4de8-90cb-bd320d2eed30</tstamps>
    </comp>
    <comp ref="D3">
      <value>YELLOW</value>
      <footprint>LED_SMD:LED_0603_1608Metric_Pad1.05x0.95mm_HandSolder</footprint>
      <fields>
        <field name="LCSC">C72038</field>
      </fields>
      <libsource lib="Device" part="LED" description="Light emitting diode"/>
      <property name="LCSC" value="C72038"/>
      <property name="Sheetname" value=""/>
      <property name="Sheetfile" value="ZDG_ELEKTRONIKA_D-class_AMP.kicad_sch"/>
      <property name="ki_description" value="Light emitting diode"/>
      <property name="ki_keywords" value="LED diode"/>
      <sheetpath names="/" tstamps="/"/>
      <tstamps>3df8bf8e-c81d-489e-8fcf-e19c20f49ba7</tstamps>
    </comp>
    <comp ref="FB1">
      <value>GZ1608D601TF</value>
      <footprint>Inductor_SMD:L_0603_1608Metric_Pad1.05x0.95mm_HandSolder</footprint>
      <fields>
        <field name="LCSC">C1002</field>
      </fields>
      <libsource lib="Device" part="FerriteBead_Small" description="Ferrite bead, small symbol"/>
      <property name="LCSC" value="C1002"/>
      <property name="Sheetname" value=""/>
      <property name="Sheetfile" value="ZDG_ELEKTRONIKA_D-class_AMP.kicad_sch"/>
      <property name="ki_description" value="Ferrite bead, small symbol"/>
      <property name="ki_keywords" value="L ferrite bead inductor filter"/>
      <sheetpath names="/" tstamps="/"/>
      <tstamps>2825e8d3-dc0c-457c-8210-3a04d8ac0922</tstamps>
    </comp>
    <comp ref="J1">
      <value>Barrel_Jack_Switch</value>
      <footprint>Connector_BarrelJack:BarrelJack_GCT_DCJ200-10-A_Horizontal</footprint>
      <libsource lib="Connector" part="Barrel_Jack_Switch" description="DC Barrel Jack with an internal switch"/>
      <property name="Sheetname" value=""/>
      <property name="Sheetfile" value="ZDG_ELEKTRONIKA_D-class_AMP.kicad_sch"/>
      <property name="ki_description" value="DC Barrel Jack with an internal switch"/>
      <property name="ki_keywords" value="DC power barrel jack connector"/>
      <sheetpath names="/" tstamps="/"/>
      <tstamps>65fc515f-3bb9-4401-b5b3-01495c240ec4</tstamps>
    </comp>
    <comp ref="J2">
      <value>OUT-</value>
      <footprint>Connector_Pin:Pin_D1.0mm_L10.0mm</footprint>
      <libsource lib="Connector" part="Conn_01x01_Pin" description="Generic connector, single row, 01x01, script generated"/>
      <property name="Sheetname" value=""/>
      <property name="Sheetfile" value="ZDG_ELEKTRONIKA_D-class_AMP.kicad_sch"/>
      <property name="ki_description" value="Generic connector, single row, 01x01, script generated"/>
      <property name="ki_keywords" value="connector"/>
      <sheetpath names="/" tstamps="/"/>
      <tstamps>7284c964-627e-4dc7-bb76-70c4f5fa6fdc</tstamps>
    </comp>
    <comp ref="J3">
      <value>OUT+</value>
      <footprint>Connector_Pin:Pin_D1.0mm_L10.0mm</footprint>
      <libsource lib="Connector" part="Conn_01x01_Pin" description="Generic connector, single row, 01x01, script generated"/>
      <property name="Sheetname" value=""/>
      <property name="Sheetfile" value="ZDG_ELEKTRONIKA_D-class_AMP.kicad_sch"/>
      <property name="ki_description" value="Generic connector, single row, 01x01, script generated"/>
      <property name="ki_keywords" value="connector"/>
      <sheetpath names="/" tstamps="/"/>
      <tstamps>792ea01f-b855-4087-92a6-f9ce491cac57</tstamps>
    </comp>
    <comp ref="J4">
      <value>OUTPUT</value>
      <footprint>Connector_Audio:Jack_6.35mm_Neutrik_NMJ4HCD2_Horizontal</footprint>
      <libsource lib="Connector_Audio" part="AudioJack2_Switch" description="Audio Jack, 2 Poles (Mono / TS), Switched Pole (Normalling)"/>
      <property name="Sheetname" value=""/>
      <property name="Sheetfile" value="ZDG_ELEKTRONIKA_D-class_AMP.kicad_sch"/>
      <property name="ki_description" value="Audio Jack, 2 Poles (Mono / TS), Switched Pole (Normalling)"/>
      <property name="ki_keywords" value="audio jack receptacle mono headphones phone TS connector"/>
      <sheetpath names="/" tstamps="/"/>
      <tstamps>141aaba9-e2f1-42b5-b121-331324fbd182</tstamps>
    </comp>
    <comp ref="J5">
      <value>INPUT</value>
      <footprint>Connector_Audio:Jack_6.35mm_Neutrik_NMJ4HCD2_Horizontal</footprint>
      <libsource lib="Connector_Audio" part="AudioJack2_Switch" description="Audio Jack, 2 Poles (Mono / TS), Switched Pole (Normalling)"/>
      <property name="Sheetname" value=""/>
      <property name="Sheetfile" value="ZDG_ELEKTRONIKA_D-class_AMP.kicad_sch"/>
      <property name="ki_description" value="Audio Jack, 2 Poles (Mono / TS), Switched Pole (Normalling)"/>
      <property name="ki_keywords" value="audio jack receptacle mono headphones phone TS connector"/>
      <sheetpath names="/" tstamps="/"/>
      <tstamps>7cedecd8-ef9f-4eea-9172-a68f7752cefc</tstamps>
    </comp>
    <comp ref="JP1">
      <value>SolderJumper_2_Open</value>
      <footprint>Jumper:SolderJumper-2_P1.3mm_Open_Pad1.0x1.5mm</footprint>
      <libsource lib="Jumper" part="SolderJumper_2_Open" description="Solder Jumper, 2-pole, open"/>
      <property name="Sheetname" value=""/>
      <property name="Sheetfile" value="ZDG_ELEKTRONIKA_D-class_AMP.kicad_sch"/>
      <property name="ki_description" value="Solder Jumper, 2-pole, open"/>
      <property name="ki_keywords" value="solder jumper SPST"/>
      <sheetpath names="/" tstamps="/"/>
      <tstamps>0c6cf5bc-92ef-43a5-84a2-b968e96a90de</tstamps>
    </comp>
    <comp ref="JP2">
      <value>SolderJumper_2_Open</value>
      <footprint>Jumper:SolderJumper-2_P1.3mm_Open_Pad1.0x1.5mm</footprint>
      <libsource lib="Jumper" part="SolderJumper_2_Open" description="Solder Jumper, 2-pole, open"/>
      <property name="Sheetname" value=""/>
      <property name="Sheetfile" value="ZDG_ELEKTRONIKA_D-class_AMP.kicad_sch"/>
      <property name="ki_description" value="Solder Jumper, 2-pole, open"/>
      <property name="ki_keywords" value="solder jumper SPST"/>
      <sheetpath names="/" tstamps="/"/>
      <tstamps>ab0c5295-bb6a-4fbd-99c8-dc9c171f9768</tstamps>
    </comp>
    <comp ref="JP3">
      <value>SolderJumper_2_Open</value>
      <footprint>Jumper:SolderJumper-2_P1.3mm_Open_Pad1.0x1.5mm</footprint>
      <libsource lib="Jumper" part="SolderJumper_2_Open" description="Solder Jumper, 2-pole, open"/>
      <property name="Sheetname" value=""/>
      <property name="Sheetfile" value="ZDG_ELEKTRONIKA_D-class_AMP.kicad_sch"/>
      <property name="ki_description" value="Solder Jumper, 2-pole, open"/>
      <property name="ki_keywords" value="solder jumper SPST"/>
      <sheetpath names="/" tstamps="/"/>
      <tstamps>ddd76c70-ca57-4cfe-ae2c-d560568e21d3</tstamps>
    </comp>
    <comp ref="JP4">
      <value>SolderJumper_2_Open</value>
      <footprint>Jumper:SolderJumper-2_P1.3mm_Open_Pad1.0x1.5mm</footprint>
      <libsource lib="Jumper" part="SolderJumper_2_Open" description="Solder Jumper, 2-pole, open"/>
      <property name="Sheetname" value=""/>
      <property name="Sheetfile" value="ZDG_ELEKTRONIKA_D-class_AMP.kicad_sch"/>
      <property name="ki_description" value="Solder Jumper, 2-pole, open"/>
      <property name="ki_keywords" value="solder jumper SPST"/>
      <sheetpath names="/" tstamps="/"/>
      <tstamps>e5e29f8e-2737-4183-b8ff-2ba51c65c738</tstamps>
    </comp>
    <comp ref="JP5">
      <value>SolderJumper_2_Bridged</value>
      <footprint>Jumper:SolderJumper-2_P1.3mm_Bridged2Bar_Pad1.0x1.5mm</footprint>
      <libsource lib="Jumper" part="SolderJumper_2_Bridged" description="Solder Jumper, 2-pole, closed/bridged"/>
      <property name="Sheetname" value=""/>
      <property name="Sheetfile" value="ZDG_ELEKTRONIKA_D-class_AMP.kicad_sch"/>
      <property name="ki_description" value="Solder Jumper, 2-pole, closed/bridged"/>
      <property name="ki_keywords" value="solder jumper SPST"/>
      <sheetpath names="/" tstamps="/"/>
      <tstamps>5462ea71-fd17-4b93-9fc3-5922cb4ab494</tstamps>
    </comp>
    <comp ref="L1">
      <value>33uH</value>
      <footprint>Inductor_SMD:L_TDK_VLS6045EX_VLS6045AF</footprint>
      <fields>
        <field name="Mouser">810-VLS6045EX-330M</field>
      </fields>
      <libsource lib="Device" part="L" description="Inductor"/>
      <property name="Mouser" value="810-VLS6045EX-330M"/>
      <property name="Sheetname" value=""/>
      <property name="Sheetfile" value="ZDG_ELEKTRONIKA_D-class_AMP.kicad_sch"/>
      <property name="ki_description" value="Inductor"/>
      <property name="ki_keywords" value="inductor choke coil reactor magnetic"/>
      <sheetpath names="/" tstamps="/"/>
      <tstamps>26c05f80-f982-4a9f-a888-f238ab765bf5</tstamps>
    </comp>
    <comp ref="L2">
      <value>33uH</value>
      <footprint>Inductor_SMD:L_TDK_VLS6045EX_VLS6045AF</footprint>
      <fields>
        <field name="Mouser">810-VLS6045EX-330M</field>
      </fields>
      <libsource lib="Device" part="L" description="Inductor"/>
      <property name="Mouser" value="810-VLS6045EX-330M"/>
      <property name="Sheetname" value=""/>
      <property name="Sheetfile" value="ZDG_ELEKTRONIKA_D-class_AMP.kicad_sch"/>
      <property name="ki_description" value="Inductor"/>
      <property name="ki_keywords" value="inductor choke coil reactor magnetic"/>
      <sheetpath names="/" tstamps="/"/>
      <tstamps>155ea9d9-1565-44ed-b430-f1b301771459</tstamps>
    </comp>
    <comp ref="R1">
      <value>100k</value>
      <footprint>Resistor_SMD:R_0603_1608Metric_Pad0.98x0.95mm_HandSolder</footprint>
      <fields>
        <field name="LCSC">C25803</field>
      </fields>
      <libsource lib="Device" part="R" description="Resistor"/>
      <property name="LCSC" value="C25803"/>
      <property name="Sheetname" value=""/>
      <property name="Sheetfile" value="ZDG_ELEKTRONIKA_D-class_AMP.kicad_sch"/>
      <property name="ki_description" value="Resistor"/>
      <property name="ki_keywords" value="R res resistor"/>
      <sheetpath names="/" tstamps="/"/>
      <tstamps>595ebc11-3ad4-49df-94d3-8b07922c16c2</tstamps>
    </comp>
    <comp ref="R2">
      <value>5k1</value>
      <footprint>Resistor_SMD:R_0603_1608Metric_Pad0.98x0.95mm_HandSolder</footprint>
      <fields>
        <field name="LCSC">C23186</field>
      </fields>
      <libsource lib="Device" part="R" description="Resistor"/>
      <property name="LCSC" value="C23186"/>
      <property name="Sheetname" value=""/>
      <property name="Sheetfile" value="ZDG_ELEKTRONIKA_D-class_AMP.kicad_sch"/>
      <property name="ki_description" value="Resistor"/>
      <property name="ki_keywords" value="R res resistor"/>
      <sheetpath names="/" tstamps="/"/>
      <tstamps>1abf38db-8a11-4827-a493-8cc6783bb9c4</tstamps>
    </comp>
    <comp ref="R3">
      <value>5k1</value>
      <footprint>Resistor_SMD:R_0603_1608Metric_Pad0.98x0.95mm_HandSolder</footprint>
      <fields>
        <field name="LCSC">C23186</field>
      </fields>
      <libsource lib="Device" part="R" description="Resistor"/>
      <property name="LCSC" value="C23186"/>
      <property name="Sheetname" value=""/>
      <property name="Sheetfile" value="ZDG_ELEKTRONIKA_D-class_AMP.kicad_sch"/>
      <property name="ki_description" value="Resistor"/>
      <property name="ki_keywords" value="R res resistor"/>
      <sheetpath names="/" tstamps="/"/>
      <tstamps>7543ab8a-7e1c-4a24-8b6f-b100859160b2</tstamps>
    </comp>
    <comp ref="R4">
      <value>100k</value>
      <footprint>Resistor_SMD:R_0603_1608Metric_Pad0.98x0.95mm_HandSolder</footprint>
      <fields>
        <field name="LCSC">C25803</field>
      </fields>
      <libsource lib="Device" part="R" description="Resistor"/>
      <property name="LCSC" value="C25803"/>
      <property name="Sheetname" value=""/>
      <property name="Sheetfile" value="ZDG_ELEKTRONIKA_D-class_AMP.kicad_sch"/>
      <property name="ki_description" value="Resistor"/>
      <property name="ki_keywords" value="R res resistor"/>
      <sheetpath names="/" tstamps="/"/>
      <tstamps>05fe423c-5db3-42e4-b7ce-4b8643ec7738</tstamps>
    </comp>
    <comp ref="U1">
      <value>TPA3112D1</value>
      <footprint>Package_SO:HTSSOP-28-1EP_4.4x9.7mm_P0.65mm_EP2.85x5.4mm</footprint>
      <libsource lib="ZDG_ELEKTRONIKA_D-class_AMP" part="tpa3112D1" description=""/>
      <property name="Sheetname" value=""/>
      <property name="Sheetfile" value="ZDG_ELEKTRONIKA_D-class_AMP.kicad_sch"/>
      <sheetpath names="/" tstamps="/"/>
      <tstamps>856b1d5f-8227-4999-bd51-41686d83f519</tstamps>
    </comp>
  </components>
  <libparts>
    <libpart lib="Connector" part="Barrel_Jack_Switch">
      <description>DC Barrel Jack with an internal switch</description>
      <docs>~</docs>
      <footprints>
        <fp>BarrelJack*</fp>
      </footprints>
      <fields>
        <field name="Reference">J</field>
        <field name="Value">Barrel_Jack_Switch</field>
        <field name="Datasheet">~</field>
      </fields>
      <pins>
        <pin num="1" name="" type="passive"/>
        <pin num="2" name="" type="passive"/>
        <pin num="3" name="" type="passive"/>
      </pins>
    </libpart>
    <libpart lib="Connector" part="Conn_01x01_Pin">
      <description>Generic connector, single row, 01x01, script generated</description>
      <docs>~</docs>
      <footprints>
        <fp>Connector*:*_1x??_*</fp>
      </footprints>
      <fields>
        <field name="Reference">J</field>
        <field name="Value">Conn_01x01_Pin</field>
        <field name="Datasheet">~</field>
      </fields>
      <pins>
        <pin num="1" name="Pin_1" type="passive"/>
      </pins>
    </libpart>
    <libpart lib="Connector_Audio" part="AudioJack2_Switch">
      <description>Audio Jack, 2 Poles (Mono / TS), Switched Pole (Normalling)</description>
      <docs>~</docs>
      <footprints>
        <fp>Jack*</fp>
      </footprints>
      <fields>
        <field name="Reference">J</field>
        <field name="Value">AudioJack2_Switch</field>
        <field name="Datasheet">~</field>
      </fields>
      <pins>
        <pin num="S" name="" type="passive"/>
        <pin num="SN" name="" type="passive"/>
        <pin num="T" name="" type="passive"/>
        <pin num="TN" name="" type="passive"/>
      </pins>
    </libpart>
    <libpart lib="Device" part="C">
      <description>Unpolarized capacitor</description>
      <docs>~</docs>
      <footprints>
        <fp>C_*</fp>
      </footprints>
      <fields>
        <field name="Reference">C</field>
        <field name="Value">C</field>
        <field name="Datasheet">~</field>
      </fields>
      <pins>
        <pin num="1" name="" type="passive"/>
        <pin num="2" name="" type="passive"/>
      </pins>
    </libpart>
    <libpart lib="Device" part="C_Polarized">
      <description>Polarized capacitor</description>
      <docs>~</docs>
      <footprints>
        <fp>CP_*</fp>
      </footprints>
      <fields>
        <field name="Reference">C</field>
        <field name="Value">C_Polarized</field>
        <field name="Datasheet">~</field>
      </fields>
      <pins>
        <pin num="1" name="" type="passive"/>
        <pin num="2" name="" type="passive"/>
      </pins>
    </libpart>
    <libpart lib="Device" part="D_TVS">
      <description>Bidirectional transient-voltage-suppression diode</description>
      <docs>~</docs>
      <footprints>
        <fp>TO-???*</fp>
        <fp>*_Diode_*</fp>
        <fp>*SingleDiode*</fp>
        <fp>D_*</fp>
      </footprints>
      <fields>
        <field name="Reference">D</field>
        <field name="Value">D_TVS</field>
        <field name="Datasheet">~</field>
      </fields>
      <pins>
        <pin num="1" name="A1" type="passive"/>
        <pin num="2" name="A2" type="passive"/>
      </pins>
    </libpart>
    <libpart lib="Device" part="FerriteBead_Small">
      <description>Ferrite bead, small symbol</description>
      <docs>~</docs>
      <footprints>
        <fp>Inductor_*</fp>
        <fp>L_*</fp>
        <fp>*Ferrite*</fp>
      </footprints>
      <fields>
        <field name="Reference">FB</field>
        <field name="Value">FerriteBead_Small</field>
        <field name="Datasheet">~</field>
      </fields>
      <pins>
        <pin num="1" name="" type="passive"/>
        <pin num="2" name="" type="passive"/>
      </pins>
    </libpart>
    <libpart lib="Device" part="L">
      <description>Inductor</description>
      <docs>~</docs>
      <footprints>
        <fp>Choke_*</fp>
        <fp>*Coil*</fp>
        <fp>Inductor_*</fp>
        <fp>L_*</fp>
      </footprints>
      <fields>
        <field name="Reference">L</field>
        <field name="Value">L</field>
        <field name="Datasheet">~</field>
      </fields>
      <pins>
        <pin num="1" name="1" type="passive"/>
        <pin num="2" name="2" type="passive"/>
      </pins>
    </libpart>
    <libpart lib="Device" part="LED">
      <description>Light emitting diode</description>
      <docs>~</docs>
      <footprints>
        <fp>LED*</fp>
        <fp>LED_SMD:*</fp>
        <fp>LED_THT:*</fp>
      </footprints>
      <fields>
        <field name="Reference">D</field>
        <field name="Value">LED</field>
        <field name="Datasheet">~</field>
      </fields>
      <pins>
        <pin num="1" name="K" type="passive"/>
        <pin num="2" name="A" type="passive"/>
      </pins>
    </libpart>
    <libpart lib="Device" part="R">
      <description>Resistor</description>
      <docs>~</docs>
      <footprints>
        <fp>R_*</fp>
      </footprints>
      <fields>
        <field name="Reference">R</field>
        <field name="Value">R</field>
        <field name="Datasheet">~</field>
      </fields>
      <pins>
        <pin num="1" name="" type="passive"/>
        <pin num="2" name="" type="passive"/>
      </pins>
    </libpart>
    <libpart lib="Jumper" part="SolderJumper_2_Bridged">
      <description>Solder Jumper, 2-pole, closed/bridged</description>
      <docs>~</docs>
      <footprints>
        <fp>SolderJumper*Bridged*</fp>
      </footprints>
      <fields>
        <field name="Reference">JP</field>
        <field name="Value">SolderJumper_2_Bridged</field>
        <field name="Datasheet">~</field>
      </fields>
      <pins>
        <pin num="1" name="A" type="passive"/>
        <pin num="2" name="B" type="passive"/>
      </pins>
    </libpart>
    <libpart lib="Jumper" part="SolderJumper_2_Open">
      <description>Solder Jumper, 2-pole, open</description>
      <docs>~</docs>
      <footprints>
        <fp>SolderJumper*Open*</fp>
      </footprints>
      <fields>
        <field name="Reference">JP</field>
        <field name="Value">SolderJumper_2_Open</field>
        <field name="Datasheet">~</field>
      </fields>
      <pins>
        <pin num="1" name="A" type="passive"/>
        <pin num="2" name="B" type="passive"/>
      </pins>
    </libpart>
    <libpart lib="Mechanical" part="MountingHole_Pad">
      <description>Mounting Hole with connection</description>
      <docs>~</docs>
      <footprints>
        <fp>MountingHole*Pad*</fp>
      </footprints>
      <fields>
        <field name="Reference">H</field>
        <field name="Value">MountingHole_Pad</field>
        <field name="Datasheet">~</field>
      </fields>
      <pins>
        <pin num="1" name="1" type="input"/>
      </pins>
    </libpart>
    <libpart lib="ZDG_ELEKTRONIKA_D-class_AMP" part="tpa3112D1">
      <fields>
        <field name="Reference">U</field>
        <field name="Value">TPA3112D1</field>
        <field name="Footprint">Package_SO:HTSSOP-28-1EP_4.4x9.7mm_P0.65mm_EP2.85x5.4mm</field>
      </fields>
      <pins>
        <pin num="1" name="~{SD}" type="unspecified"/>
        <pin num="2" name="~{FAULT}" type="unspecified"/>
        <pin num="3" name="GND" type="unspecified"/>
        <pin num="4" name="GND" type="unspecified"/>
        <pin num="5" name="GAIN0" type="unspecified"/>
        <pin num="6" name="GAIN1" type="unspecified"/>
        <pin num="7" name="AVCC" type="unspecified"/>
        <pin num="8" name="AGND" type="unspecified"/>
        <pin num="9" name="GVDD" type="unspecified"/>
        <pin num="10" name="PLIMIT" type="unspecified"/>
        <pin num="11" name="INN" type="unspecified"/>
        <pin num="12" name="INP" type="unspecified"/>
        <pin num="13" name="NC" type="unspecified"/>
        <pin num="14" name="AVCC" type="unspecified"/>
        <pin num="15" name="PVCC" type="unspecified"/>
        <pin num="16" name="PVCC" type="unspecified"/>
        <pin num="17" name="BSN" type="unspecified"/>
        <pin num="18" name="OUTN" type="unspecified"/>
        <pin num="19" name="PGND" type="unspecified"/>
        <pin num="20" name="OUTN" type="unspecified"/>
        <pin num="21" name="BSN" type="unspecified"/>
        <pin num="22" name="BSP" type="unspecified"/>
        <pin num="23" name="OUTP" type="unspecified"/>
        <pin num="24" name="PGND" type="unspecified"/>
        <pin num="25" name="OUTP" type="unspecified"/>
        <pin num="26" name="BSP" type="unspecified"/>
        <pin num="27" name="PVCC" type="unspecified"/>
        <pin num="28" name="PVCC" type="unspecified"/>
        <pin num="29" name="PPAD" type="input"/>
      </pins>
    </libpart>
  </libparts>
  <libraries>
    <library logical="Connector">
      <uri>C:\Program Files\KiCad\7.0\share\kicad\symbols\/Connector.kicad_sym</uri>
    </library>
    <library logical="Connector_Audio">
      <uri>C:\Program Files\KiCad\7.0\share\kicad\symbols\/Connector_Audio.kicad_sym</uri>
    </library>
    <library logical="Device">
      <uri>C:\Program Files\KiCad\7.0\share\kicad\symbols\/Device.kicad_sym</uri>
    </library>
    <library logical="Jumper">
      <uri>C:\Program Files\KiCad\7.0\share\kicad\symbols\/Jumper.kicad_sym</uri>
    </library>
    <library logical="Mechanical">
      <uri>C:\Program Files\KiCad\7.0\share\kicad\symbols\/Mechanical.kicad_sym</uri>
    </library>
    <library logical="ZDG_ELEKTRONIKA_D-class_AMP">
      <uri>C:\elektronika\ZDG_ELEKTRONIKA_D-class_AMP/ZDG_ELEKTRONIKA_D-class_AMP.kicad_sym</uri>
    </library>
  </libraries>
  <nets>
    <net code="1" name="+12V">
      <node ref="C1" pin="1" pintype="passive"/>
      <node ref="C2" pin="1" pintype="passive"/>
      <node ref="C3" pin="1" pintype="passive"/>
      <node ref="C4" pin="1" pintype="passive"/>
      <node ref="C5" pin="1" pintype="passive"/>
      <node ref="C6" pin="1" pintype="passive"/>
      <node ref="D1" pin="2" pinfunction="A2" pintype="passive"/>
      <node ref="FB1" pin="1" pintype="passive"/>
      <node ref="J1" pin="1" pintype="passive"/>
      <node ref="R1" pin="1" pintype="passive"/>
      <node ref="R3" pin="2" pintype="passive"/>
      <node ref="U1" pin="15" pinfunction="PVCC" pintype="unspecified"/>
      <node ref="U1" pin="16" pinfunction="PVCC" pintype="unspecified"/>
      <node ref="U1" pin="27" pinfunction="PVCC" pintype="unspecified"/>
      <node ref="U1" pin="28" pinfunction="PVCC" pintype="unspecified"/>
    </net>
    <net code="2" name="/AVCC">
      <node ref="C7" pin="1" pintype="passive"/>
      <node ref="FB1" pin="2" pintype="passive"/>
      <node ref="JP1" pin="2" pinfunction="B" pintype="passive"/>
      <node ref="JP2" pin="2" pinfunction="B" pintype="passive"/>
      <node ref="R4" pin="1" pintype="passive"/>
      <node ref="U1" pin="7" pinfunction="AVCC" pintype="unspecified"/>
    </net>
    <net code="3" name="/GAIN0">
      <node ref="JP1" pin="1" pinfunction="A" pintype="passive"/>
      <node ref="JP4" pin="2" pinfunction="B" pintype="passive"/>
      <node ref="U1" pin="5" pinfunction="GAIN0" pintype="unspecified"/>
    </net>
    <net code="4" name="/GAIN1">
      <node ref="JP2" pin="1" pinfunction="A" pintype="passive"/>
      <node ref="JP3" pin="2" pinfunction="B" pintype="passive"/>
      <node ref="U1" pin="6" pinfunction="GAIN1" pintype="unspecified"/>
    </net>
    <net code="5" name="/INPUT">
      <node ref="C10" pin="1" pintype="passive"/>
      <node ref="J5" pin="T" pintype="passive"/>
      <node ref="J5" pin="TN" pintype="passive"/>
    </net>
    <net code="6" name="Earth">
      <node ref="C15" pin="1" pintype="passive"/>
      <node ref="C16" pin="2" pintype="passive"/>
      <node ref="C17" pin="2" pintype="passive"/>
      <node ref="C18" pin="2" pintype="passive"/>
    </net>
    <net code="7" name="GND">
      <node ref="C1" pin="2" pintype="passive"/>
      <node ref="C13" pin="1" pintype="passive"/>
      <node ref="C14" pin="2" pintype="passive"/>
      <node ref="C15" pin="2" pintype="passive"/>
      <node ref="C16" pin="1" pintype="passive"/>
      <node ref="C17" pin="1" pintype="passive"/>
      <node ref="C18" pin="1" pintype="passive"/>
      <node ref="C2" pin="2" pintype="passive"/>
      <node ref="C3" pin="2" pintype="passive"/>
      <node ref="C4" pin="2" pintype="passive"/>
      <node ref="C5" pin="2" pintype="passive"/>
      <node ref="C6" pin="2" pintype="passive"/>
      <node ref="C8" pin="2" pintype="passive"/>
      <node ref="D1" pin="1" pinfunction="A1" pintype="passive"/>
      <node ref="D2" pin="1" pinfunction="K" pintype="passive"/>
      <node ref="D3" pin="1" pinfunction="K" pintype="passive"/>
      <node ref="J1" pin="2" pintype="passive"/>
      <node ref="J1" pin="3" pintype="passive"/>
      <node ref="JP3" pin="1" pinfunction="A" pintype="passive"/>
      <node ref="JP4" pin="1" pinfunction="A" pintype="passive"/>
      <node ref="JP5" pin="2" pinfunction="B" pintype="passive"/>
      <node ref="U1" pin="19" pinfunction="PGND" pintype="unspecified"/>
      <node ref="U1" pin="24" pinfunction="PGND" pintype="unspecified"/>
      <node ref="U1" pin="29" pinfunction="PPAD" pintype="input"/>
      <node ref="U1" pin="3" pinfunction="GND" pintype="unspecified"/>
      <node ref="U1" pin="4" pinfunction="GND" pintype="unspecified"/>
    </net>
    <net code="8" name="GNDA">
      <node ref="C7" pin="2" pintype="passive"/>
      <node ref="C9" pin="1" pintype="passive"/>
      <node ref="J5" pin="S" pintype="passive"/>
      <node ref="J5" pin="SN" pintype="passive"/>
      <node ref="JP5" pin="1" pinfunction="A" pintype="passive"/>
      <node ref="U1" pin="8" pinfunction="AGND" pintype="unspecified"/>
    </net>
    <net code="9" name="Net-(C11-Pad1)">
      <node ref="C11" pin="1" pintype="passive"/>
      <node ref="L2" pin="1" pinfunction="1" pintype="passive"/>
      <node ref="U1" pin="18" pinfunction="OUTN" pintype="unspecified"/>
      <node ref="U1" pin="20" pinfunction="OUTN" pintype="unspecified"/>
    </net>
    <net code="10" name="Net-(C11-Pad2)">
      <node ref="C11" pin="2" pintype="passive"/>
      <node ref="U1" pin="17" pinfunction="BSN" pintype="unspecified"/>
      <node ref="U1" pin="21" pinfunction="BSN" pintype="unspecified"/>
    </net>
    <net code="11" name="Net-(C12-Pad1)">
      <node ref="C12" pin="1" pintype="passive"/>
      <node ref="L1" pin="1" pinfunction="1" pintype="passive"/>
      <node ref="U1" pin="23" pinfunction="OUTP" pintype="unspecified"/>
      <node ref="U1" pin="25" pinfunction="OUTP" pintype="unspecified"/>
    </net>
    <net code="12" name="Net-(C12-Pad2)">
      <node ref="C12" pin="2" pintype="passive"/>
      <node ref="U1" pin="22" pinfunction="BSP" pintype="unspecified"/>
      <node ref="U1" pin="26" pinfunction="BSP" pintype="unspecified"/>
    </net>
    <net code="13" name="Net-(D2-A)">
      <node ref="D2" pin="2" pinfunction="A" pintype="passive"/>
      <node ref="R2" pin="1" pintype="passive"/>
    </net>
    <net code="14" name="Net-(D3-A)">
      <node ref="D3" pin="2" pinfunction="A" pintype="passive"/>
      <node ref="R3" pin="1" pintype="passive"/>
    </net>
    <net code="15" name="Net-(J2-Pin_1)">
      <node ref="C14" pin="1" pintype="passive"/>
      <node ref="J2" pin="1" pinfunction="Pin_1" pintype="passive"/>
      <node ref="J4" pin="S" pintype="passive"/>
      <node ref="J4" pin="SN" pintype="passive"/>
      <node ref="L2" pin="2" pinfunction="2" pintype="passive"/>
    </net>
    <net code="16" name="Net-(J3-Pin_1)">
      <node ref="C13" pin="2" pintype="passive"/>
      <node ref="J3" pin="1" pinfunction="Pin_1" pintype="passive"/>
      <node ref="J4" pin="T" pintype="passive"/>
      <node ref="J4" pin="TN" pintype="passive"/>
      <node ref="L1" pin="2" pinfunction="2" pintype="passive"/>
    </net>
    <net code="17" name="Net-(R4-Pad2)">
      <node ref="R4" pin="2" pintype="passive"/>
      <node ref="U1" pin="14" pinfunction="AVCC" pintype="unspecified"/>
    </net>
    <net code="18" name="Net-(U1-GVDD)">
      <node ref="C8" pin="1" pintype="passive"/>
      <node ref="U1" pin="10" pinfunction="PLIMIT" pintype="unspecified"/>
      <node ref="U1" pin="9" pinfunction="GVDD" pintype="unspecified"/>
    </net>
    <net code="19" name="Net-(U1-INN)">
      <node ref="C9" pin="2" pintype="passive"/>
      <node ref="U1" pin="11" pinfunction="INN" pintype="unspecified"/>
    </net>
    <net code="20" name="Net-(U1-INP)">
      <node ref="C10" pin="2" pintype="passive"/>
      <node ref="U1" pin="12" pinfunction="INP" pintype="unspecified"/>
    </net>
    <net code="21" name="Net-(U1-~{FAULT})">
      <node ref="R1" pin="2" pintype="passive"/>
      <node ref="R2" pin="2" pintype="passive"/>
      <node ref="U1" pin="1" pinfunction="~{SD}" pintype="unspecified"/>
      <node ref="U1" pin="2" pinfunction="~{FAULT}" pintype="unspecified"/>
    </net>
    <net code="22" name="unconnected-(U1-NC-Pad13)">
      <node ref="U1" pin="13" pinfunction="NC" pintype="unspecified+no_connect"/>
    </net>
  </nets>
</export>
